.gitignore
.pre-commit-config.yaml
MANIFEST.in
README.txt
setup.py
XStatic_mapbox_gl_leaflet.egg-info/PKG-INFO
XStatic_mapbox_gl_leaflet.egg-info/SOURCES.txt
XStatic_mapbox_gl_leaflet.egg-info/dependency_links.txt
XStatic_mapbox_gl_leaflet.egg-info/namespace_packages.txt
XStatic_mapbox_gl_leaflet.egg-info/not-zip-safe
XStatic_mapbox_gl_leaflet.egg-info/requires.txt
XStatic_mapbox_gl_leaflet.egg-info/top_level.txt
debian/changelog
debian/control
debian/rules
debian/source/format
xstatic/__init__.py
xstatic/pkg/__init__.py
xstatic/pkg/mapbox_gl_leaflet/__init__.py
xstatic/pkg/mapbox_gl_leaflet/data/leaflet-mapbox-gl.js
xstatic/pkg/mapbox_gl_leaflet/data/mapbox-gl.css
xstatic/pkg/mapbox_gl_leaflet/data/mapbox-gl.js