Metadata-Version: 2.4
Name: XStatic-mapbox-gl-leaflet
Version: 0.0.16.1
Summary: mapbox-gl-leaflet 0.0.16 (XStatic packaging standard)
Home-page: https://github.com/mapbox/mapbox-gl-leaflet
Maintainer: Entr’ouvert
Maintainer-email: info@entrouvert.com
License: (same as mapbox-gl-leaflet)
Keywords: mapbox_gl_leaflet xstatic
Platform: any
Requires-Dist: XStatic-Leaflet
Dynamic: description
Dynamic: home-page
Dynamic: keywords
Dynamic: license
Dynamic: maintainer
Dynamic: maintainer-email
Dynamic: platform
Dynamic: requires-dist
Dynamic: summary
